fortran2cc2fortran/README.MD
fortran2cc2fortran/__init__.py
fortran2cc2fortran/requirements.txt
fortran2cc2fortran/thirdparty.json
fortran2cc2fortran-0.10.dist-info/LICENSE.rst
fortran2cc2fortran-0.10.dist-info/METADATA
fortran2cc2fortran-0.10.dist-info/WHEEL
fortran2cc2fortran-0.10.dist-info/top_level.txt
fortran2cc2fortran-0.10.dist-info/RECORD
