Metadata-Version: 2.1
Name: fortran2cc2fortran
Version: 0.10
Summary: Fortran to C / C to Fortran (nested) index converter
Home-page: https://github.com/hansalemaos/fortran2cc2fortran
Author: Johannes Fischer
Author-email: aulasparticularesdealemaosp@gmail.com
License: MIT
Keywords: numpy,C,fortran
Classifier: Development Status :: 4 - Beta
Classifier: Programming Language :: Python :: 3 :: Only
Classifier: Programming Language :: Python :: 3.10
Classifier: Topic :: Software Development :: Libraries :: Python Modules
Classifier: Topic :: Utilities
License-File: LICENSE.rst
